{
"meta":{"test_sets":[],"test_metrics":[],"learn_metrics":[{"best_value":"Min","name":"RMSE"}],"launch_mode":"Train","parameters":"","iteration_count":100,"learn_sets":["learn"],"name":"experiment"},
"iterations":[
{"learn":[14.005006],"iteration":0,"passed_time":0.001359391333,"remaining_time":0.1345797419},
{"learn":[13.14441192],"iteration":1,"passed_time":0.002485281182,"remaining_time":0.1217787779},
{"learn":[12.34258257],"iteration":2,"passed_time":0.003614504206,"remaining_time":0.1168689693},
{"learn":[11.64527793],"iteration":3,"passed_time":0.00449852631,"remaining_time":0.1079646315},
{"learn":[11.02766183],"iteration":4,"passed_time":0.005620292783,"remaining_time":0.1067855629},
{"learn":[10.43485794],"iteration":5,"passed_time":0.006734811841,"remaining_time":0.1055120522},
{"learn":[9.890641275],"iteration":6,"passed_time":0.007856367261,"remaining_time":0.1043774508},
{"learn":[9.492161212],"iteration":7,"passed_time":0.008985005006,"remaining_time":0.1033275576},
{"learn":[9.105082953],"iteration":8,"passed_time":0.01037581674,"remaining_time":0.1049110359},
{"learn":[8.674157135],"iteration":9,"passed_time":0.0115947076,"remaining_time":0.1043523684},
{"learn":[8.341743544],"iteration":10,"passed_time":0.01270708549,"remaining_time":0.1028118735},
{"learn":[8.049372916],"iteration":11,"passed_time":0.0138129602,"remaining_time":0.1012950415},
{"learn":[7.757318612],"iteration":12,"passed_time":0.01489927291,"remaining_time":0.09971051872},
{"learn":[7.522206899],"iteration":13,"passed_time":0.01603655309,"remaining_time":0.09851025468},
{"learn":[7.297756655],"iteration":14,"passed_time":0.01715573982,"remaining_time":0.09721585895},
{"learn":[7.088359431],"iteration":15,"passed_time":0.01821842958,"remaining_time":0.09564675529},
{"learn":[6.882113791],"iteration":16,"passed_time":0.0193411613,"remaining_time":0.09443037576},
{"learn":[6.704728832],"iteration":17,"passed_time":0.02046156225,"remaining_time":0.09321378359},
{"learn":[6.563881962],"iteration":18,"passed_time":0.02162207391,"remaining_time":0.09217831509},
{"learn":[6.418790279],"iteration":19,"passed_time":0.02268520991,"remaining_time":0.09074083964},
{"learn":[6.315756953],"iteration":20,"passed_time":0.0239410499,"remaining_time":0.09006394964},
{"learn":[6.210157751],"iteration":21,"passed_time":0.02510244369,"remaining_time":0.08899957309},
{"learn":[6.115058449],"iteration":22,"passed_time":0.02615389175,"remaining_time":0.08755868107},
{"learn":[6.014819884],"iteration":23,"passed_time":0.02725580741,"remaining_time":0.08631005679},
{"learn":[5.93117229],"iteration":24,"passed_time":0.0283161913,"remaining_time":0.08494857389},
{"learn":[5.844857622],"iteration":25,"passed_time":0.02945134946,"remaining_time":0.08382307153},
{"learn":[5.771145213],"iteration":26,"passed_time":0.03061616337,"remaining_time":0.08277703429},
{"learn":[5.704018229],"iteration":27,"passed_time":0.03174283461,"remaining_time":0.08162443185},
{"learn":[5.665806474],"iteration":28,"passed_time":0.03296056296,"remaining_time":0.08069655069},
{"learn":[5.616500369],"iteration":29,"passed_time":0.03405816028,"remaining_time":0.07946904064},
{"learn":[5.558023666],"iteration":30,"passed_time":0.03521719495,"remaining_time":0.07838665973},
{"learn":[5.510080976],"iteration":31,"passed_time":0.03633380615,"remaining_time":0.07720933806},
{"learn":[5.468747792],"iteration":32,"passed_time":0.03743494654,"remaining_time":0.0760042854},
{"learn":[5.429275534],"iteration":33,"passed_time":0.03884011942,"remaining_time":0.07539552594},
{"learn":[5.402117324],"iteration":34,"passed_time":0.03995498743,"remaining_time":0.07420211951},
{"learn":[5.367635151],"iteration":35,"passed_time":0.04103876942,"remaining_time":0.0729578123},
{"learn":[5.345181232],"iteration":36,"passed_time":0.04218849557,"remaining_time":0.07183446543},
{"learn":[5.319151269],"iteration":37,"passed_time":0.04330611223,"remaining_time":0.07065734101},
{"learn":[5.296134146],"iteration":38,"passed_time":0.04439454619,"remaining_time":0.06943762353},
{"learn":[5.269629003],"iteration":39,"passed_time":0.0455059347,"remaining_time":0.06825890205},
{"learn":[5.251147059],"iteration":40,"passed_time":0.04664275907,"remaining_time":0.06712006792},
{"learn":[5.248003302],"iteration":41,"passed_time":0.0471222804,"remaining_time":0.06507362531},
{"learn":[5.232376509],"iteration":42,"passed_time":0.04838962027,"remaining_time":0.06414438035},
{"learn":[5.213524255],"iteration":43,"passed_time":0.04948090554,"remaining_time":0.06297569796},
{"learn":[5.189691584],"iteration":44,"passed_time":0.0506473711,"remaining_time":0.06190234246},
{"learn":[5.166052198],"iteration":45,"passed_time":0.05171283711,"remaining_time":0.060706374},
{"learn":[5.140406659],"iteration":46,"passed_time":0.05298239781,"remaining_time":0.05974610817},
{"learn":[5.118929684],"iteration":47,"passed_time":0.05408930826,"remaining_time":0.05859675061},
{"learn":[5.108792602],"iteration":48,"passed_time":0.05524741062,"remaining_time":0.05750240697},
{"learn":[5.098141225],"iteration":49,"passed_time":0.05631287548,"remaining_time":0.05631287548},
{"learn":[5.085926393],"iteration":50,"passed_time":0.05739924488,"remaining_time":0.0551482941},
{"learn":[5.067816804],"iteration":51,"passed_time":0.0584709919,"remaining_time":0.05397322329},
{"learn":[5.049834901],"iteration":52,"passed_time":0.05960342131,"remaining_time":0.05285586418},
{"learn":[5.03838627],"iteration":53,"passed_time":0.06066214244,"remaining_time":0.05167515838},
{"learn":[5.033534248],"iteration":54,"passed_time":0.06140729121,"remaining_time":0.05024232917},
{"learn":[5.023726885],"iteration":55,"passed_time":0.06254772147,"remaining_time":0.0491446383},
{"learn":[5.01290392],"iteration":56,"passed_time":0.06361979713,"remaining_time":0.04799388205},
{"learn":[5.005569127],"iteration":57,"passed_time":0.06473682546,"remaining_time":0.04687839085},
{"learn":[4.989969032],"iteration":58,"passed_time":0.06601403461,"remaining_time":0.04587415965},
{"learn":[4.976762446],"iteration":59,"passed_time":0.06741000392,"remaining_time":0.04494000261},
{"learn":[4.967222715],"iteration":60,"passed_time":0.06857872709,"remaining_time":0.04384541568},
{"learn":[4.954407599],"iteration":61,"passed_time":0.0697058304,"remaining_time":0.04272292831},
{"learn":[4.942125056],"iteration":62,"passed_time":0.07082503053,"remaining_time":0.04159565285},
{"learn":[4.930230716],"iteration":63,"passed_time":0.0719632457,"remaining_time":0.0404793257},
{"learn":[4.921695642],"iteration":64,"passed_time":0.07312248606,"remaining_time":0.03937364634},
{"learn":[4.906405625],"iteration":65,"passed_time":0.07418801795,"remaining_time":0.03821806985},
{"learn":[4.894330248],"iteration":66,"passed_time":0.07527346883,"remaining_time":0.03707499211},
{"learn":[4.88211557],"iteration":67,"passed_time":0.07636919157,"remaining_time":0.03593844309},
{"learn":[4.877946398],"iteration":68,"passed_time":0.07751903339,"remaining_time":0.03482739181},
{"learn":[4.863182126],"iteration":69,"passed_time":0.07863349997,"remaining_time":0.03370007142},
{"learn":[4.84646533],"iteration":70,"passed_time":0.07970819752,"remaining_time":0.03255686941},
{"learn":[4.838014752],"iteration":71,"passed_time":0.08092023128,"remaining_time":0.03146897883},
{"learn":[4.82981137],"iteration":72,"passed_time":0.08224343763,"remaining_time":0.0304188057},
{"learn":[4.817094767],"iteration":73,"passed_time":0.08346137014,"remaining_time":0.02932426518},
{"learn":[4.808314151],"iteration":74,"passed_time":0.08457715436,"remaining_time":0.02819238479},
{"learn":[4.796235023],"iteration":75,"passed_time":0.08569817774,"remaining_time":0.02706258245},
{"learn":[4.784434534],"iteration":76,"passed_time":0.08684688655,"remaining_time":0.0259412778},
{"learn":[4.774402487],"iteration":77,"passed_time":0.08797494438,"remaining_time":0.02481344585},
{"learn":[4.76731896],"iteration":78,"passed_time":0.08907665205,"remaining_time":0.02367860371},
{"learn":[4.75934113],"iteration":79,"passed_time":0.09020366419,"remaining_time":0.02255091605},
{"learn":[4.754106378],"iteration":80,"passed_time":0.09126672818,"remaining_time":0.02140824488},
{"learn":[4.744002932],"iteration":81,"passed_time":0.09236335565,"remaining_time":0.02027488295},
{"learn":[4.731700554],"iteration":82,"passed_time":0.09347722968,"remaining_time":0.01914593861},
{"learn":[4.723284153],"iteration":83,"passed_time":0.09456686216,"remaining_time":0.01801273565},
{"learn":[4.712232782],"iteration":84,"passed_time":0.09607270289,"remaining_time":0.01695400639},
{"learn":[4.703046867],"iteration":85,"passed_time":0.09737048182,"remaining_time":0.01585100867},
{"learn":[4.698601855],"iteration":86,"passed_time":0.09860043397,"remaining_time":0.01473339818},
{"learn":[4.692429407],"iteration":87,"passed_time":0.100007745,"remaining_time":0.01363741977},
{"learn":[4.675027364],"iteration":88,"passed_time":0.1012822392,"remaining_time":0.01251802956},
{"learn":[4.662368584],"iteration":89,"passed_time":0.1024324196,"remaining_time":0.01138137995},
{"learn":[4.646206172],"iteration":90,"passed_time":0.103559005,"remaining_time":0.0102420994},
{"learn":[4.641245848],"iteration":91,"passed_time":0.1046598696,"remaining_time":0.00910085823},
{"learn":[4.633900435],"iteration":92,"passed_time":0.1057757757,"remaining_time":0.007961617524},
{"learn":[4.624738236],"iteration":93,"passed_time":0.1068666875,"remaining_time":0.006821277925},
{"learn":[4.612798287],"iteration":94,"passed_time":0.1079633468,"remaining_time":0.005682281408},
{"learn":[4.605222001],"iteration":95,"passed_time":0.1090788743,"remaining_time":0.004544953098},
{"learn":[4.601725912],"iteration":96,"passed_time":0.1107715713,"remaining_time":0.003425924884},
{"learn":[4.59722371],"iteration":97,"passed_time":0.1119431086,"remaining_time":0.002284553237},
{"learn":[4.580235665],"iteration":98,"passed_time":0.1130881966,"remaining_time":0.001142305016},
{"learn":[4.57591791],"iteration":99,"passed_time":0.1141709107,"remaining_time":0}
]}